wx_chatbot_client/__init__.py
wx_chatbot_client/py.typed
wx_chatbot_client/web.py
wx_chatbot_client/client/favicon.ico
wx_chatbot_client/client/index.html
wx_chatbot_client/client/css/142.eb735fce.css
wx_chatbot_client/client/css/142.eb735fce.css.gz
wx_chatbot_client/client/css/364.e784a9ec.css
wx_chatbot_client/client/css/364.e784a9ec.css.gz
wx_chatbot_client/client/css/40.4b83b9e0.css
wx_chatbot_client/client/css/40.4b83b9e0.css.gz
wx_chatbot_client/client/css/750.e21f17ba.css
wx_chatbot_client/client/css/750.e21f17ba.css.gz
wx_chatbot_client/client/css/app.5443a0b1.css
wx_chatbot_client/client/css/app.5443a0b1.css.gz
wx_chatbot_client/client/css/fail.6ad4026d.css
wx_chatbot_client/client/fonts/element-icons.f1a45d74.ttf
wx_chatbot_client/client/fonts/element-icons.ff18efd1.woff
wx_chatbot_client/client/fonts/iconfont.1d8d388a.ttf
wx_chatbot_client/client/js/142-legacy.a4ec0f46.js
wx_chatbot_client/client/js/142-legacy.a4ec0f46.js.gz
wx_chatbot_client/client/js/142.a4ec0f46.js
wx_chatbot_client/client/js/142.a4ec0f46.js.gz
wx_chatbot_client/client/js/364-legacy.c39af242.js
wx_chatbot_client/client/js/364-legacy.c39af242.js.gz
wx_chatbot_client/client/js/364.c39af242.js
wx_chatbot_client/client/js/364.c39af242.js.gz
wx_chatbot_client/client/js/40-legacy.33110ade.js
wx_chatbot_client/client/js/40-legacy.33110ade.js.gz
wx_chatbot_client/client/js/40.33110ade.js
wx_chatbot_client/client/js/40.33110ade.js.gz
wx_chatbot_client/client/js/750-legacy.a78ed7b1.js
wx_chatbot_client/client/js/750-legacy.a78ed7b1.js.gz
wx_chatbot_client/client/js/750.a78ed7b1.js
wx_chatbot_client/client/js/750.a78ed7b1.js.gz
wx_chatbot_client/client/js/app-legacy.4f9fa794.js
wx_chatbot_client/client/js/app-legacy.4f9fa794.js.gz
wx_chatbot_client/client/js/app-legacy.54947003.js
wx_chatbot_client/client/js/app-legacy.54947003.js.gz
wx_chatbot_client/client/js/app-legacy.74c944a4.js
wx_chatbot_client/client/js/app-legacy.74c944a4.js.gz
wx_chatbot_client/client/js/app-legacy.dfcce418.js
wx_chatbot_client-0.2.0.dist-info/METADATA
wx_chatbot_client-0.2.0.dist-info/WHEEL
wx_chatbot_client-0.2.0.dist-info/RECORD
