Metadata-Version: 2.4
Name: wx-chatbot-client
Version: 0.2.0
Summary: wx-ai-starter客户端
Author-email: Wang Bingfei <wangbingfei@weixiangcn.com>, Hu Jiagli <hujiali@weixiangcn.com>
Requires-Python: >=3.12
Requires-Dist: fastapi[standard]>=0.115.12
